fastapi_rapidoc/__init__.py
fastapi_rapidoc-0.1.7.dist-info/WHEEL
fastapi_rapidoc-0.1.7.dist-info/METADATA
fastapi_rapidoc-0.1.7.dist-info/RECORD
