Metadata-Version: 2.1
Name: fastapi_rapidoc
Version: 0.1.7
Summary: Quickly add RapiDoc to FastAPI
Author-email: Mawoka <mawoka-myblock@e.email>
